README.md
setup.py
bluffpaddingcypher/__init__.py
bluffpaddingcypher/cypher.py
bluffpaddingcypher.egg-info/PKG-INFO
bluffpaddingcypher.egg-info/SOURCES.txt
bluffpaddingcypher.egg-info/dependency_links.txt
bluffpaddingcypher.egg-info/top_level.txt