Metadata-Version: 2.1
Name: bluffpaddingcypher
Version: 1.0
Summary: BluffPadding Cipher Algorithm: A Python-based encryption tool combining random prefixes/suffixes with character shifts for enhanced text obfuscation.
Home-page: https://github.com/neuqs90/bluffpadding-cypher-algorithm.git
Author: Bhavya Padaliya
License: MIT
Keywords: encryption,cipher,obfuscation,security
Classifier: Development Status :: 3 - Alpha
Classifier: Intended Audience :: Developers
Classifier: Programming Language :: Python :: 3
Classifier: Programming Language :: Python :: 3.6
Classifier: Programming Language :: Python :: 3.7
Classifier: Programming Language :: Python :: 3.8
Classifier: Programming Language :: Python :: 3.9
Classifier: Programming Language :: Python :: 3.10
Classifier: Topic :: Security :: Cryptography
Requires-Python: >=3.6
